xxh3-0.0.0.dist-info/METADATA
xxh3-0.0.0.dist-info/WHEEL
xxh3/__init__.py
xxh3/xxh3.pypy38-pp73-x86_64-linux-gnu.so
xxh3-0.0.0.dist-info/RECORD
