Metadata-Version: 2.1
Name: xxh3
Version: 0.0.0
Classifier: Development Status :: 4 - Beta
Classifier: License :: OSI Approved :: MIT License
Classifier: License :: OSI Approved :: Apache Software License
Classifier: Programming Language :: Python
Classifier: Programming Language :: Python :: 3
Classifier: Programming Language :: Python :: 3 :: Only
Classifier: Programming Language :: Rust
Summary: XXH3 hash function
Home-Page: https://github.com/cberner/xxh3
Author: Christopher Berner <christopherberner@gmail.com>
Author-email: Christopher Berner <christopherberner@gmail.com>
License: MIT OR Apache-2.0
Requires-Python: >= 3.7
Project-URL: Source Code, https://github.com/cberner/xxh3
